<?xml version="1.0" encoding="utf-8" ?><dwsync><file name="style_page.css" server="www1097.onamae.ne.jp" local="3810615725" remote="3810615720" Dst="-1" /><file name="style_top.css" server="www1097.onamae.ne.jp" local="3810811272" remote="3810811260" Dst="-1" /><file name="style_common.css" server="www1097.onamae.ne.jp" local="3810811243" remote="3810811260" Dst="-1" /><file name="bootstrap.min.css" server="ftp.lolipop.jp/relativ/test/deepvision/" local="3811153484" remote="3811213200" Dst="-1" /><file name="animate.min.css" server="ftp.lolipop.jp/relativ/test/deepvision/" local="3811137078" remote="3811213200" Dst="-1" /><file name="style_page.css" server="ftp.lolipop.jp/relativ/test/deepvision/" local="3821533615" remote="3821533920" Dst="-1" /><file name="style_top.css" server="ftp.lolipop.jp/relativ/test/deepvision/" local="3820633559" remote="3820634460" Dst="-1" /><file name="responsive.css" server="ftp.lolipop.jp/relativ/test/deepvision/" local="3820543653" remote="3820563420" Dst="-1" /><file name="style_common.css" server="ftp.lolipop.jp/relativ/test/deepvision/" local="3820633559" remote="3820634460" Dst="-1" /><file name="style.css" server="ftp.lolipop.jp/relativ/test/deepvision/" local="3820544051" remote="3820563420" Dst="-1" /><file name="font-awesome.min.css" server="ftp.lolipop.jp/relativ/test/deepvision/" local="3811118750" remote="3811213200" Dst="-1" /><file name="style_header.css" server="ftp.lolipop.jp/relativ/test/deepvision/" local="3820563121" remote="3820563420" Dst="-1" /><file name="style_service.css" server="ftp.lolipop.jp/relativ/test/deepvision/" local="3820634566" remote="3820636200" Dst="-1" /></dwsync>